pyhidromotic/__init__.py
pyhidromotic/client.py
pyhidromotic/const.py
pyhidromotic/py.typed
pyhidromotic-0.1.3.dist-info/licenses/LICENSE
pyhidromotic-0.1.3.dist-info/METADATA
pyhidromotic-0.1.3.dist-info/WHEEL
pyhidromotic-0.1.3.dist-info/top_level.txt
pyhidromotic-0.1.3.dist-info/RECORD
