Metadata-Version: 2.4
Name: pyhidromotic
Version: 0.1.3
Summary: Python client for Hidromotic CHI Smart irrigation controllers
Author-email: bulju <bulju@users.noreply.github.com>
License: GPL-3.0-or-later
Project-URL: Homepage, https://github.com/bulju/pyhidromotic
Project-URL: Bug Tracker, https://github.com/bulju/pyhidromotic/issues
Project-URL: Repository, https://github.com/bulju/pyhidromotic
Keywords: hidromotic,irrigation,smart home,home assistant
Classifier: Development Status :: 4 - Beta
Classifier: Intended Audience :: Developers
Classifier: License :: OSI Approved :: GNU General Public License v3 or later (GPLv3+)
Classifier: Operating System :: OS Independent
Classifier: Programming Language :: Python :: 3
Classifier: Programming Language :: Python :: 3.11
Classifier: Programming Language :: Python :: 3.12
Classifier: Programming Language :: Python :: 3.13
Classifier: Topic :: Home Automation
Classifier: Typing :: Typed
Requires-Python: >=3.11
License-File: LICENSE
Requires-Dist: aiohttp>=3.8.0
Provides-Extra: dev
Requires-Dist: pytest>=7.0; extra == "dev"
Requires-Dist: pytest-asyncio>=0.21; extra == "dev"
Requires-Dist: pytest-cov>=4.0; extra == "dev"
Requires-Dist: ruff>=0.1.0; extra == "dev"
Requires-Dist: mypy>=1.0; extra == "dev"
Dynamic: license-file
